tapas/__init__.py
tapas/app.py
tapas/constants.py
tapas/index.py
tapas/io.py
tapas/loader.py
tapas/params.py
tapas/parsers.py
tapas/tapas.version
tapas/templater.py
tapas/util.py
tapas/tools/__init__.py
tapas/tools/common.py
tapas/tools/git.py
tapas/tools/license.py
tapas/tools/tapas_integration_tests.py
tapas-1.0.2.post9.dist-info/LICENSE
tapas-1.0.2.post9.dist-info/METADATA
tapas-1.0.2.post9.dist-info/WHEEL
tapas-1.0.2.post9.dist-info/entry_points.txt
tapas-1.0.2.post9.dist-info/top_level.txt
tapas-1.0.2.post9.dist-info/RECORD
