Metadata-Version: 2.1
Name: tapas
Version: 1.0.2.post9
Summary: A simple general purpose scaffold tool
Home-page: https://github.com/tapas-scaffold-tool/tapas
Author: Kirill Sulim
Author-email: kirillsulim@gmail.com
License: MIT
Keywords: scaffold build generator generate
Classifier: Development Status :: 3 - Alpha
Classifier: Environment :: Console
Classifier: Intended Audience :: Developers
Classifier: Topic :: Software Development :: Build Tools
Classifier: License :: OSI Approved :: MIT License
Classifier: Programming Language :: Python :: 3
Classifier: Programming Language :: Python :: 3.6
Classifier: Programming Language :: Python :: 3.7
Requires-Python: ~=3.6
License-File: LICENSE
Requires-Dist: rusty-results (~=1.1.1)
Requires-Dist: Jinja2 (~=2.10)
Requires-Dist: gitsnapshot (~=0.1.1)
Requires-Dist: appdirs (~=1.4.3)
Requires-Dist: PyYAML (~=5.1)
Requires-Dist: requests (~=2.21.0)
Requires-Dist: GitPython (~=3.0.5)
Requires-Dist: lice (~=0.5)
Requires-Dist: tabulate (~=0.8.7)
Requires-Dist: markupsafe (==2.0.1)
